setup.py
distributions_2/Binomialdistribution.py
distributions_2/Gaussiandistribution.py
distributions_2/Generaldistribution.py
distributions_2/__init__.py
distributions_2.egg-info/PKG-INFO
distributions_2.egg-info/SOURCES.txt
distributions_2.egg-info/dependency_links.txt
distributions_2.egg-info/not-zip-safe
distributions_2.egg-info/top_level.txt