Metadata-Version: 1.0
Name: distributions-2
Version: 0.1
Summary: Gaussian and Binomial distributions
Home-page: UNKNOWN
Author: bayode
Author-email: UNKNOWN
License: UNKNOWN
Platform: UNKNOWN
